aelf_python_client/__init__.py
aelf_python_client/client.py
aelf_python_client/schemas/__init__.py
aelf_python_client/schemas/complies.py
aelf_python_client/schemas/enums/__init__.py
aelf_python_client/schemas/enums/couleurs.py
aelf_python_client/schemas/enums/zones.py
aelf_python_client/schemas/informations.py
aelf_python_client/schemas/laudes.py
aelf_python_client/schemas/lecture.py
aelf_python_client/schemas/lectures.py
aelf_python_client/schemas/messe.py
aelf_python_client/schemas/none.py
aelf_python_client/schemas/responses/__init__.py
aelf_python_client/schemas/responses/complies.py
aelf_python_client/schemas/responses/informations.py
aelf_python_client/schemas/responses/laudes.py
aelf_python_client/schemas/responses/lectures.py
aelf_python_client/schemas/responses/messes.py
aelf_python_client/schemas/responses/none.py
aelf_python_client/schemas/responses/sexte.py
aelf_python_client/schemas/responses/tierce.py
aelf_python_client/schemas/responses/vepres.py
aelf_python_client/schemas/sexte.py
aelf_python_client/schemas/text.py
aelf_python_client/schemas/tierce.py
aelf_python_client/schemas/vepres.py
aelf_python_client-0.1.0.dist-info/METADATA
aelf_python_client-0.1.0.dist-info/WHEEL
aelf_python_client-0.1.0.dist-info/RECORD
