Metadata-Version: 2.3
Name: aelf_python_client
Version: 0.1.0
Summary: Python client for the AELF API (https://api.aelf.org/)
License: MIT
Author: Thamin
Author-email: github@thamin.ovh
Requires-Python: >=3.13
Classifier: License :: OSI Approved :: MIT License
Classifier: Programming Language :: Python :: 3
Classifier: Programming Language :: Python :: 3.13
Requires-Dist: aiohttp (>=3.11.16,<4.0.0)
Requires-Dist: async-timeout (>=5.0.1,<6.0.0)
Requires-Dist: pydantic (>=2.11.3,<3.0.0)
